convolution_reverb/__init__.py
convolution_reverb/core.py
convolution_reverb-0.1.6.dist-info/LICENSE
convolution_reverb-0.1.6.dist-info/METADATA
convolution_reverb-0.1.6.dist-info/WHEEL
convolution_reverb-0.1.6.dist-info/top_level.txt
convolution_reverb-0.1.6.dist-info/RECORD
