Metadata-Version: 2.2
Name: convolution-reverb
Version: 0.1.6
Summary: A Python package for applying convolution reverb to audio files using PyTorch
Author-email: Your Name <your.email@example.com>
License: MIT License
Project-URL: Homepage, https://github.com/yourusername/convolution-reverb
Project-URL: Repository, https://github.com/yourusername/convolution-reverb.git
Keywords: audio,reverb,convolution,pytorch,torchaudio
Classifier: License :: OSI Approved :: MIT License
Classifier: Programming Language :: Python :: 3
Classifier: Programming Language :: Python :: 3.8
Classifier: Programming Language :: Python :: 3.9
Classifier: Programming Language :: Python :: 3.10
Requires-Python: >=3.8
License-File: LICENSE
Requires-Dist: torch>=2.0.0
Requires-Dist: torchaudio>=2.0.0
